{"modelTopology":{"class_name":"Model","config":{"name":"model977","layers":[{"name":"input977","class_name":"InputLayer","config":{"batch_input_shape":[null,3],"dtype":"float32","sparse":false,"name":"input977"},"inbound_nodes":[]},{"name":"dense_Dense5857","class_name":"Dense","config":{"units":16,"activation":"relu","use_bias":true,"kernel_initializer":{"class_name":"VarianceScaling","config":{"scale":1,"mode":"fan_avg","distribution":"normal","seed":null}},"bias_initializer":{"class_name":"Zeros","config":{}},"kernel_regularizer":null,"bias_regularizer":null,"activity_regularizer":null,"kernel_constraint":null,"bias_constraint":null,"name":"dense_Dense5857","trainable":true},"inbound_nodes":[[["input977",0,0,{}]]]},{"name":"dense_Dense5858","class_name":"Dense","config":{"units":16,"activation":"relu","use_bias":true,"kernel_initializer":{"class_name":"VarianceScaling","config":{"scale":1,"mode":"fan_avg","distribution":"normal","seed":null}},"bias_initializer":{"class_name":"Zeros","config":{}},"kernel_regularizer":null,"bias_regularizer":null,"activity_regularizer":null,"kernel_constraint":null,"bias_constraint":null,"name":"dense_Dense5858","trainable":true},"inbound_nodes":[[["dense_Dense5857",0,0,{}]]]},{"name":"dense_Dense5859","class_name":"Dense","config":{"units":8,"activation":"relu","use_bias":true,"kernel_initializer":{"class_name":"VarianceScaling","config":{"scale":1,"mode":"fan_avg","distribution":"normal","seed":null}},"bias_initializer":{"class_name":"Zeros","config":{}},"kernel_regularizer":null,"bias_regularizer":null,"activity_regularizer":null,"kernel_constraint":null,"bias_constraint":null,"name":"dense_Dense5859","trainable":true},"inbound_nodes":[[["dense_Dense5858",0,0,{}]]]},{"name":"dense_Dense5860","class_name":"Dense","config":{"units":1,"activation":"relu","use_bias":true,"kernel_initializer":{"class_name":"VarianceScaling","config":{"scale":1,"mode":"fan_avg","distribution":"normal","seed":null}},"bias_initializer":{"class_name":"Zeros","config":{}},"kernel_regularizer":null,"bias_regularizer":null,"activity_regularizer":null,"kernel_constraint":null,"bias_constraint":null,"name":"dense_Dense5860","trainable":true},"inbound_nodes":[[["dense_Dense5859",0,0,{}]]]},{"name":"dense_Dense5861","class_name":"Dense","config":{"units":16,"activation":"relu","use_bias":true,"kernel_initializer":{"class_name":"VarianceScaling","config":{"scale":1,"mode":"fan_avg","distribution":"normal","seed":null}},"bias_initializer":{"class_name":"Zeros","config":{}},"kernel_regularizer":null,"bias_regularizer":null,"activity_regularizer":null,"kernel_constraint":null,"bias_constraint":null,"name":"dense_Dense5861","trainable":true},"inbound_nodes":[[["dense_Dense5860",0,0,{}]]]},{"name":"dense_Dense5862","class_name":"Dense","config":{"units":1,"activation":"sigmoid","use_bias":true,"kernel_initializer":{"class_name":"VarianceScaling","config":{"scale":1,"mode":"fan_avg","distribution":"normal","seed":null}},"bias_initializer":{"class_name":"Zeros","config":{}},"kernel_regularizer":null,"bias_regularizer":null,"activity_regularizer":null,"kernel_constraint":null,"bias_constraint":null,"name":"dense_Dense5862","trainable":true},"inbound_nodes":[[["dense_Dense5861",0,0,{}]]]}],"input_layers":[["input977",0,0]],"output_layers":[["dense_Dense5862",0,0]]},"keras_version":"tfjs-layers 3.9.0","backend":"tensor_flow.js"},"weightsManifest":[{"paths":["weights.bin"],"weights":[{"name":"dense_Dense5857/kernel","shape":[3,16],"dtype":"float32"},{"name":"dense_Dense5857/bias","shape":[16],"dtype":"float32"},{"name":"dense_Dense5858/kernel","shape":[16,16],"dtype":"float32"},{"name":"dense_Dense5858/bias","shape":[16],"dtype":"float32"},{"name":"dense_Dense5859/kernel","shape":[16,8],"dtype":"float32"},{"name":"dense_Dense5859/bias","shape":[8],"dtype":"float32"},{"name":"dense_Dense5860/kernel","shape":[8,1],"dtype":"float32"},{"name":"dense_Dense5860/bias","shape":[1],"dtype":"float32"},{"name":"dense_Dense5861/kernel","shape":[1,16],"dtype":"float32"},{"name":"dense_Dense5861/bias","shape":[16],"dtype":"float32"},{"name":"dense_Dense5862/kernel","shape":[16,1],"dtype":"float32"},{"name":"dense_Dense5862/bias","shape":[1],"dtype":"float32"}]}]}