{"modelTopology":{"class_name":"Model","config":{"name":"model1130","layers":[{"name":"input1130","class_name":"InputLayer","config":{"batch_input_shape":[null,3],"dtype":"float32","sparse":false,"name":"input1130"},"inbound_nodes":[]},{"name":"dense_Dense6775","class_name":"Dense","config":{"units":32,"activation":"relu","use_bias":true,"kernel_initializer":{"class_name":"VarianceScaling","config":{"scale":1,"mode":"fan_avg","distribution":"normal","seed":null}},"bias_initializer":{"class_name":"Zeros","config":{}},"kernel_regularizer":null,"bias_regularizer":null,"activity_regularizer":null,"kernel_constraint":null,"bias_constraint":null,"name":"dense_Dense6775","trainable":true},"inbound_nodes":[[["input1130",0,0,{}]]]},{"name":"dense_Dense6776","class_name":"Dense","config":{"units":32,"activation":"relu","use_bias":true,"kernel_initializer":{"class_name":"VarianceScaling","config":{"scale":1,"mode":"fan_avg","distribution":"normal","seed":null}},"bias_initializer":{"class_name":"Zeros","config":{}},"kernel_regularizer":null,"bias_regularizer":null,"activity_regularizer":null,"kernel_constraint":null,"bias_constraint":null,"name":"dense_Dense6776","trainable":true},"inbound_nodes":[[["dense_Dense6775",0,0,{}]]]},{"name":"dense_Dense6777","class_name":"Dense","config":{"units":2,"activation":"relu","use_bias":true,"kernel_initializer":{"class_name":"VarianceScaling","config":{"scale":1,"mode":"fan_avg","distribution":"normal","seed":null}},"bias_initializer":{"class_name":"Zeros","config":{}},"kernel_regularizer":null,"bias_regularizer":null,"activity_regularizer":null,"kernel_constraint":null,"bias_constraint":null,"name":"dense_Dense6777","trainable":true},"inbound_nodes":[[["dense_Dense6776",0,0,{}]]]},{"name":"dense_Dense6778","class_name":"Dense","config":{"units":4,"activation":"relu","use_bias":true,"kernel_initializer":{"class_name":"VarianceScaling","config":{"scale":1,"mode":"fan_avg","distribution":"normal","seed":null}},"bias_initializer":{"class_name":"Zeros","config":{}},"kernel_regularizer":null,"bias_regularizer":null,"activity_regularizer":null,"kernel_constraint":null,"bias_constraint":null,"name":"dense_Dense6778","trainable":true},"inbound_nodes":[[["dense_Dense6777",0,0,{}]]]},{"name":"dense_Dense6779","class_name":"Dense","config":{"units":2,"activation":"relu","use_bias":true,"kernel_initializer":{"class_name":"VarianceScaling","config":{"scale":1,"mode":"fan_avg","distribution":"normal","seed":null}},"bias_initializer":{"class_name":"Zeros","config":{}},"kernel_regularizer":null,"bias_regularizer":null,"activity_regularizer":null,"kernel_constraint":null,"bias_constraint":null,"name":"dense_Dense6779","trainable":true},"inbound_nodes":[[["dense_Dense6778",0,0,{}]]]},{"name":"dense_Dense6780","class_name":"Dense","config":{"units":1,"activation":"sigmoid","use_bias":true,"kernel_initializer":{"class_name":"VarianceScaling","config":{"scale":1,"mode":"fan_avg","distribution":"normal","seed":null}},"bias_initializer":{"class_name":"Zeros","config":{}},"kernel_regularizer":null,"bias_regularizer":null,"activity_regularizer":null,"kernel_constraint":null,"bias_constraint":null,"name":"dense_Dense6780","trainable":true},"inbound_nodes":[[["dense_Dense6779",0,0,{}]]]}],"input_layers":[["input1130",0,0]],"output_layers":[["dense_Dense6780",0,0]]},"keras_version":"tfjs-layers 3.9.0","backend":"tensor_flow.js"},"weightsManifest":[{"paths":["weights.bin"],"weights":[{"name":"dense_Dense6775/kernel","shape":[3,32],"dtype":"float32"},{"name":"dense_Dense6775/bias","shape":[32],"dtype":"float32"},{"name":"dense_Dense6776/kernel","shape":[32,32],"dtype":"float32"},{"name":"dense_Dense6776/bias","shape":[32],"dtype":"float32"},{"name":"dense_Dense6777/kernel","shape":[32,2],"dtype":"float32"},{"name":"dense_Dense6777/bias","shape":[2],"dtype":"float32"},{"name":"dense_Dense6778/kernel","shape":[2,4],"dtype":"float32"},{"name":"dense_Dense6778/bias","shape":[4],"dtype":"float32"},{"name":"dense_Dense6779/kernel","shape":[4,2],"dtype":"float32"},{"name":"dense_Dense6779/bias","shape":[2],"dtype":"float32"},{"name":"dense_Dense6780/kernel","shape":[2,1],"dtype":"float32"},{"name":"dense_Dense6780/bias","shape":[1],"dtype":"float32"}]}]}